savify/__init__.py
savify/__main__.py
savify/cli.py
savify/exceptions.py
savify/ffmpegdl.py
savify/logger.py
savify/savify.py
savify/spotify.py
savify/track.py
savify/types.py
savify/utils.py
savify-2.3.4.dist-info/AUTHORS.rst
savify-2.3.4.dist-info/LICENSE
savify-2.3.4.dist-info/METADATA
savify-2.3.4.dist-info/WHEEL
savify-2.3.4.dist-info/entry_points.txt
savify-2.3.4.dist-info/top_level.txt
savify-2.3.4.dist-info/RECORD
