Metadata-Version: 1.2
Name: savify
Version: 2.3.4
Summary: Download Spotify songs to mp3 with full metadata and cover art!
Home-page: https://github.com/LaurenceRawlings/savify
Author: Laurence Rawlings
Author-email: contact@laurencerawlings.com
License: MIT license
Keywords: savify,spotify,downloader,mp3,save,playlist
Platform: UNKNOWN
Classifier: Development Status :: 2 - Pre-Alpha
Classifier: Intended Audience :: Developers
Classifier: License :: OSI Approved :: MIT License
Classifier: Natural Language :: English
Classifier: Programming Language :: Python :: 3
Classifier: Programming Language :: Python :: 3.6
Classifier: Programming Language :: Python :: 3.7
Classifier: Programming Language :: Python :: 3.8
Requires-Python: >=3.6
